[
  {
    "Day": "2023-10-02",
    "Day D": "02",
    "Live P&L": 0,
    "Strategy P&L": 0,
    "Demo P&L": 0,
    "Test P&L": 0
  },
  {
    "Day": "2023-10-03",
    "Day D": "03",
    "Live P&L": 0,
    "Strategy P&L": 0,
    "Demo P&L": 0,
    "Test P&L": 0
  },
  {
    "Day": "2023-10-04",
    "Day D": "04",
    "Live P&L": 0,
    "Strategy P&L": 2.2142857142860004,
    "Demo P&L": -1.0354,
    "Test P&L": 3.2142857142860004
  },
  {
    "Day": "2023-10-05",
    "Day D": "05",
    "Live P&L": 0,
    "Strategy P&L": 6.166666666667,
    "Demo P&L": 0,
    "Test P&L": 6.166666666667
  },
  {
    "Day": "2023-10-06",
    "Day D": "06",
    "Live P&L": 0,
    "Strategy P&L": 0,
    "Demo P&L": 0,
    "Test P&L": 0
  },
  {
    "Day": "2023-10-09",
    "Day D": "09",
    "Live P&L": 0,
    "Strategy P&L": 0,
    "Demo P&L": 0,
    "Test P&L": 0
  },
  {
    "Day": "2023-10-10",
    "Day D": "10",
    "Live P&L": 0,
    "Strategy P&L": 3.04347826087,
    "Demo P&L": 0,
    "Test P&L": 3.04347826087
  },
  {
    "Day": "2023-10-11",
    "Day D": "11",
    "Live P&L": 0,
    "Strategy P&L": 0.0,
    "Demo P&L": 0.125,
    "Test P&L": 0
  },
  {
    "Day": "2023-10-12",
    "Day D": "12",
    "Live P&L": 0,
    "Strategy P&L": 0,
    "Demo P&L": 0,
    "Test P&L": 0
  },
  {
    "Day": "2023-10-13",
    "Day D": "13",
    "Live P&L": 0,
    "Strategy P&L": 0,
    "Demo P&L": 0,
    "Test P&L": 0
  },
  {
    "Day": "2023-10-16",
    "Day D": "16",
    "Live P&L": 0,
    "Strategy P&L": -1.0,
    "Demo P&L": 0,
    "Test P&L": -1.0
  },
  {
    "Day": "2023-10-17",
    "Day D": "17",
    "Live P&L": 0,
    "Strategy P&L": 0.0,
    "Demo P&L": 0,
    "Test P&L": 0.0
  },
  {
    "Day": "2023-10-18",
    "Day D": "18",
    "Live P&L": 0,
    "Strategy P&L": 0,
    "Demo P&L": 0,
    "Test P&L": 0
  },
  {
    "Day": "2023-10-19",
    "Day D": "19",
    "Live P&L": 0,
    "Strategy P&L": 4.3,
    "Demo P&L": 0,
    "Test P&L": 4.3
  },
  {
    "Day": "2023-10-20",
    "Day D": "20",
    "Live P&L": 0,
    "Strategy P&L": 0,
    "Demo P&L": 0,
    "Test P&L": 0
  },
  {
    "Day": "2023-10-23",
    "Day D": "23",
    "Live P&L": 0,
    "Strategy P&L": 12.0,
    "Demo P&L": 3.828822857143,
    "Test P&L": 4.857142857143
  },
  {
    "Day": "2023-10-24",
    "Day D": "24",
    "Live P&L": 0,
    "Strategy P&L": 0,
    "Demo P&L": 0,
    "Test P&L": 0
  },
  {
    "Day": "2023-10-25",
    "Day D": "25",
    "Live P&L": 0,
    "Strategy P&L": 0,
    "Demo P&L": 0,
    "Test P&L": 0
  },
  {
    "Day": "2023-10-26",
    "Day D": "26",
    "Live P&L": 0,
    "Strategy P&L": 0,
    "Demo P&L": 0,
    "Test P&L": 0
  },
  {
    "Day": "2023-10-27",
    "Day D": "27",
    "Live P&L": 0,
    "Strategy P&L": 0,
    "Demo P&L": 0,
    "Test P&L": 0
  },
  {
    "Day": "2023-10-30",
    "Day D": "30",
    "Live P&L": 0,
    "Strategy P&L": 0,
    "Demo P&L": 0,
    "Test P&L": 0
  },
  {
    "Day": "2023-10-31",
    "Day D": "31",
    "Live P&L": 0,
    "Strategy P&L": 0,
    "Demo P&L": 0,
    "Test P&L": 0
  }
]